{
  "id": 20,
  "country": "YU",
  "artist": "Baby Doll",
  "song": "Brazil",
  "videoUrls": [
    "https://www.youtube-nocookie.com/embed/o1bnHiHcHQs",
    "https://www.youtube-nocookie.com/embed/e48U0cRyqMA",
    "https://www.youtube-nocookie.com/embed/Ee3SnWD317A",
    "https://www.youtube-nocookie.com/embed/GIwUpMrsK9Y",
    "https://www.youtube-nocookie.com/embed/wX20jma3-Zk"
  ],
  "lyrics": [
    {
      "type": 0,
      "languages": [
        "serbian"
      ],
      "displayedLanguages": null,
      "title": "Brazil",
      "content": "La lalala lalala…\nLalala lalala… lalala lalala…\nLa lalala lalala…\nLalala lalala… lalala lalala…\n\nBrazil, Španija, Kolumbija, Kuba i Amerika\nSamba, rumba, cha cha cha\n\nSkini sve\nSkini cipele što pre\nSkini jaknu, farmerke\nHajde igra počinje\n\nZa tvoje usne i moj vrat\nTvoj poljubac će biti znak\nZa Ramba, Dina, šta, šta, šta\nDa sam novu igru smislila\n\nBrazil\nJedan okret to su dva\nReci hop i to su tri\nTvoje srce to smo mi\nBrazil\nMeni ne treba Brazil\nDolce vitae, cha cha cha\nSamo ti sa tobom ja\n\nSkini sve\nSkini cipele što pre\nSkini jaknu, farmerke\nHajde igra počinje\n\nZa tvoje usne i moj vrat\nTvoj poljubac će biti znak\nZa Ramba, Dina, šta, šta, šta\nDa sam novu igru smislila\n\nBrazil\nJedan okret to su dva\nReci hop i to su tri\nTvoje srce to smo mi\nBrazil\nMeni ne treba Brazil\nDolce vitae, cha cha cha\nSamo ti sa tobom ja\n\nLa lalala lalala…\nLalala lalala… lalala lalala…\nLa lalala lalala…\nLalala lalala… lalala lalala…\n\nZa tvoje usne i moj vrat\nTvoj poljubac će biti znak\nZa Ramba, Dina, šta, šta, šta\nDa sam novu igru smislila\n\nBrazil\nJedan okret to su dva\nReci hop i to su tri\nTvoje srce to smo mi\nBrazil\nMeni ne treba Brazil\nDolce vitae, cha cha cha\nSamo ti sa tobom ja\n\nBrazil\nJedan okret to su dva\nReci hop i to su tri\nTvoje srce to ѕmo mi\nBrazil\nMeni ne treba Brazil\nDolce vitae, cha cha cha\nSamo ti i ja i\nOh Brаzil"
    },
    {
      "type": 1,
      "languages": [
        "english"
      ],
      "displayedLanguages": null,
      "title": "Brazil",
      "content": "La lalala lalala…\nLalala lalala… lalala lalala…\nLa lalala lalala…\nLalala lalala… lalala lalala…\n\nBrazil, Spain, Colombia, Cuba and America\nSamba, rumba, cha cha cha\n\nTake it all off\nTake your shoes off now\nTake your jacket and pants off\nCome on, the game is starting now\n\nFor your lips and my neck\nYour kiss will be the sign\nFor Rambo, Dino, what, what, what\nI made a new dance\n\nBrazil\nOne turn-around, that's two\nSay hop and that's three\nYour heart is us\nBrazil\nI don't need Brazil\nThe sweet life, cha cha cha\nOnly you and me with you\n\nTake it all off\nTake your shoes off now\nTake your jacket and pants off\nCome on, the game is starting now\n\nFor your lips and my neck\nYour kiss will be the sign\nFor Rambo, Dino, what, what, what\nI made a new dance\n\nBrazil\nOne turn-around, that's two\nSay hop and that's three\nYour heart is us\nBrazil\nI don't need Brazil\nThe sweet life, cha cha cha\nOnly you and me with you\n\nLa lalala lalala…\nLalala lalala… lalala lalala…\nLa lalala lalala…\nLalala lalala… lalala lalala…\n\nFor your lips and my neck\nYour kiss will be the sign\nFor Rambo, Dino, what, what, what\nI made a new dance\n\nBrazil\nOne turn-around, that's two\nSay hop and that's three\nYour heart is us\nBrazil\nI don't need Brazil\nThe sweet life, cha cha cha\nOnly you and me with you\n\nBrazil\nOne turn-around, that's two\nSay hop and that's three\nYour heart is us\nBrazil\nI don't need Brazil\nThe ѕweet life, cha cha cha\nOnly you and me and\nOh Brаzil"
    }
  ],
  "bpm": 120,
  "tone": "A major",
  "artistPeople": [
    "Dragana Šarić"
  ],
  "backings": [
    "Aleksandra Kovač",
    "Kristina Kovač"
  ],
  "dancers": [
    "Marija Mačić-Tarlać",
    "Ranka",
    "W-Ice"
  ],
  "stageDirector": null,
  "composers": [
    "Zoran Vracević"
  ],
  "conductor": "Slobodan Marković",
  "lyricists": [
    "Bebi Dol"
  ],
  "writers": null,
  "broadcaster": "JRT",
  "commentators": [
    "Ksenija Urličić",
    "Miša Molk",
    "Mladen Popović"
  ],
  "jury": null,
  "spokesperson": "Mebrura Topolovac"
}